Metadata-Version: 2.2
Name: accusnv
Version: 1.0.0.5
Summary: High-accuracy SNV calling for bacterial isolates using AccuSNV
Author: Lieberman Lab
License: MIT
Requires-Python: >=3.9,<3.10
License-File: LICENSE.md
Requires-Dist: numpy
Requires-Dist: pandas
Requires-Dist: scipy
Requires-Dist: matplotlib
Requires-Dist: statsmodels
Requires-Dist: torch<2.7,>=2.6
Requires-Dist: biopython==1.78
Requires-Dist: cutadapt
Requires-Dist: pulp==2.7.0
Requires-Dist: tqdm
Requires-Dist: bcbio-gff==0.6.9
Dynamic: author
Dynamic: description
Dynamic: description-content-type
Dynamic: license
Dynamic: requires-dist
Dynamic: requires-python
Dynamic: summary
